tablestore_agent_storage/__init__.py
tablestore_agent_storage/client.py
tablestore_agent_storage/models.py
tablestore_agent_storage-1.0.2.dist-info/METADATA
tablestore_agent_storage-1.0.2.dist-info/WHEEL
tablestore_agent_storage-1.0.2.dist-info/top_level.txt
tablestore_agent_storage-1.0.2.dist-info/RECORD
