Metadata-Version: 2.4
Name: tablestore-agent-storage
Version: 1.0.2
Summary: A Python SDK for agent storage
Requires-Python: >=3.8
Requires-Dist: oss2>=2.18.0
Requires-Dist: tablestore>=6.3.9
Provides-Extra: dev
Requires-Dist: pytest>=7.0.0; extra == "dev"
Requires-Dist: black>=23.0.0; extra == "dev"
Requires-Dist: flake8>=6.0.0; extra == "dev"
